darkprop/__init__.py
darkprop/_darkpropy.cpython-310-x86_64-linux-gnu.so
darkprop-0.3.0.dist-info/METADATA
darkprop-0.3.0.dist-info/WHEEL
darkprop-0.3.0.dist-info/entry_points.txt
darkprop-0.3.0.dist-info/RECORD
darkprop-0.3.0.dist-info/licenses/LICENSE
darkprop.libs/libsz-0deeef7d.so.2.0.1
darkprop.libs/libspdlog-a0a9d586.so.1.5.0
darkprop.libs/libaec-91f0ca0f.so.0.0.8
darkprop.libs/libhdf5-b5e70f84.so.103.1.0
darkprop.libs/libfmt-8375f6bf.so.6.2.1
darkprop.libs/libgsl-b64c76bc.so.23.1.0
darkprop.libs/libgslcblas-cd2c2030.so.0.0.0
