Metadata-Version: 2.1
Name: darkprop
Version: 0.3.0
Summary: Python wrapper for DarkProp
Keywords: dark matter simulation Monte Carlo
Home-page: http://yfzhou.itp.ac.cn/darkprop
Author-Email: Chen Xia <xiachen1996@outlook.com>
Maintainer-Email: Chen Xia <xiachen1996@outlook.com>
License: MIT License
Classifier: Programming Language :: Python :: 3 :: Only
Classifier: Programming Language :: Python :: 3.8
Classifier: Programming Language :: Python :: 3.9
Classifier: Programming Language :: Python :: 3.10
Classifier: Programming Language :: Python :: 3.11
Classifier: Programming Language :: Python :: 3.12
Classifier: Programming Language :: C++
Classifier: License :: OSI Approved :: MIT License
Classifier: Operating System :: POSIX :: Linux
Classifier: Topic :: Scientific/Engineering :: Physics
Classifier: Development Status :: 3 - Alpha
Project-URL: Homepage, http://yfzhou.itp.ac.cn/darkprop
Requires-Python: >=3.8
License-File: LICENSE
